mcp_d3_server/__init__.py
mcp_d3_server/models.py
mcp_d3_server/server.py
mcp_d3_server/services.py
mcp_d3_server-1.0.2.dist-info/METADATA
mcp_d3_server-1.0.2.dist-info/WHEEL
mcp_d3_server-1.0.2.dist-info/entry_points.txt
mcp_d3_server-1.0.2.dist-info/licenses/LICENSE
mcp_d3_server-1.0.2.dist-info/RECORD
